CHANGES.rst
LICENSE
MANIFEST.in
README.rst
setup.cfg
setup.py
deform_treepy/__init__.py
deform_treepy/testing.py
deform_treepy/widget.py
deform_treepy.egg-info/PKG-INFO
deform_treepy.egg-info/SOURCES.txt
deform_treepy.egg-info/dependency_links.txt
deform_treepy.egg-info/not-zip-safe
deform_treepy.egg-info/requires.txt
deform_treepy.egg-info/top_level.txt
deform_treepy/locale/treepy.pot
deform_treepy/locale/fr/LC_MESSAGES/treepy.mo
deform_treepy/locale/fr/LC_MESSAGES/treepy.po
deform_treepy/static/css/treepy.css
deform_treepy/static/js/treepy.js
deform_treepy/static/js/treepy_langs.js
deform_treepy/static/select2/.editorconfig
deform_treepy/static/select2/.jshintignore
deform_treepy/static/select2/.jshintrc
deform_treepy/static/select2/CONTRIBUTING.md
deform_treepy/static/select2/Gruntfile.js
deform_treepy/static/select2/LICENSE.md
deform_treepy/static/select2/README.md
deform_treepy/static/select2/bower.json
deform_treepy/static/select2/component.json
deform_treepy/static/select2/composer.json
deform_treepy/static/select2/package.json
deform_treepy/static/select2/select2.jquery.json
deform_treepy/static/select2/dist/css/select2.css
deform_treepy/static/select2/dist/css/select2.min.css
deform_treepy/static/select2/dist/js/select2.amd.full.js
deform_treepy/static/select2/dist/js/select2.amd.js
deform_treepy/static/select2/dist/js/select2.full.js
deform_treepy/static/select2/dist/js/select2.full.min.js
deform_treepy/static/select2/dist/js/select2.js
deform_treepy/static/select2/dist/js/select2.min.js
deform_treepy/static/select2/dist/js/i18n/az.js
deform_treepy/static/select2/dist/js/i18n/bg.js
deform_treepy/static/select2/dist/js/i18n/da.js
deform_treepy/static/select2/dist/js/i18n/de.js
deform_treepy/static/select2/dist/js/i18n/en.js
deform_treepy/static/select2/dist/js/i18n/es.js
deform_treepy/static/select2/dist/js/i18n/et.js
deform_treepy/static/select2/dist/js/i18n/eu.js
deform_treepy/static/select2/dist/js/i18n/fi.js
deform_treepy/static/select2/dist/js/i18n/fr.js
deform_treepy/static/select2/dist/js/i18n/gl.js
deform_treepy/static/select2/dist/js/i18n/hr.js
deform_treepy/static/select2/dist/js/i18n/hu.js
deform_treepy/static/select2/dist/js/i18n/id.js
