Metadata-Version: 1.1
Name: deform-treepy
Version: 1.0.1
Summary: A tree widget for deform
Home-page: https://github.com/ecreall/deform_treepy/
Author: Amen Souissi
Author-email: amensouissi@ecreall.com
License: AGPLv3+
Keywords: web forms form tree widget
Platform: UNKNOWN
Classifier: Programming Language :: Python
Classifier: Programming Language :: Python :: 3.4
Classifier: Framework :: Pyramid
Classifier: Topic :: Internet :: WWW/HTTP
Classifier: Topic :: Internet :: WWW/HTTP :: WSGI :: Application
Classifier: License :: OSI Approved :: GNU Affero General Public License v3 or later (AGPLv3+)
